{
  "바코드": "11002026021500404_001",
  "검사차수": 1,
  "측정시간": "2026-02-15 02:46:13",
  "측정횟수": 3,
  "측정데이터": [
    {
      "순번": 1,
      "전압_R": 219.92,
      "전압_S": 221.11,
      "전압_T": 217.01,
      "전류_R": 15.24,
      "전류_S": 14.53,
      "전류_T": 15.06,
      "주파수_R": 59.17,
      "주파수_S": 60.76,
      "주파수_T": 59.61,
      "전력": 10090.2
    },
    {
      "순번": 2,
      "전압_R": 221.71,
      "전압_S": 219.13,
      "전압_T": 223.23,
      "전류_R": 15.81,
      "전류_S": 14.9,
      "전류_T": 15.21,
      "주파수_R": 60.73,
      "주파수_S": 59.94,
      "주파수_T": 60.32,
      "전력": 10327.2
    },
    {
      "순번": 3,
      "전압_R": 221.71,
      "전압_S": 219.13,
      "전압_T": 223.23,
      "전류_R": 15.81,
      "전류_S": 14.9,
      "전류_T": 15.21,
      "주파수_R": 60.73,
      "주파수_S": 59.94,
      "주파수_T": 60.32,
      "전력": 10327.2
    }
  ]
}