{
  "정보": {
    "D-DATA": "1303",
    "바코드": "13032026021500295_001",
    "날짜": "20260215"
  },
  "제품정보": {
    "제품명": "TFB-F16BS",
    "전원": "1Φ 220V, 60HZ",
    "용량": "195 W",
    "전류": "R:1A (단상)"
  },
  "전원타입": "단상",
  "1차검사결과": {
    "저항값측정결과": "OK",
    "공급전원": "221.7V / 60.5Hz",
    "측정결과": {
      "R전압": "221.3 V",
      "R전류": "15.33 A",
      "R주파수": "59.9 Hz",
      "전력": "10234.4 W",
      "소음": "OK"
    },
    "판정": "NG1"
  },
  "1차검사일시": "2026-02-15 12:28:59",
  "검사완료차수": 1,
  "최종저장시간": "2026-02-15 12:28:59"
}