{
  "바코드": "11002026021500963_001",
  "검사차수": 1,
  "측정시간": "2026-02-15 02:47:37",
  "측정횟수": 3,
  "측정데이터": [
    {
      "순번": 1,
      "전압_R": 220.93,
      "전압_S": 222.11,
      "전압_T": 218.62,
      "전류_R": 15.22,
      "전류_S": 14.72,
      "전류_T": 15.36,
      "주파수_R": 59.79,
      "주파수_S": 58.85,
      "주파수_T": 60.66,
      "전력": 10177.3
    },
    {
      "순번": 2,
      "전압_R": 220.93,
      "전압_S": 222.11,
      "전압_T": 218.62,
      "전류_R": 15.22,
      "전류_S": 14.72,
      "전류_T": 15.36,
      "주파수_R": 59.79,
      "주파수_S": 58.85,
      "주파수_T": 60.66,
      "전력": 10177.3
    },
    {
      "순번": 3,
      "전압_R": 220.93,
      "전압_S": 222.11,
      "전압_T": 218.62,
      "전류_R": 15.22,
      "전류_S": 14.72,
      "전류_T": 15.36,
      "주파수_R": 59.79,
      "주파수_S": 58.85,
      "주파수_T": 60.66,
      "전력": 10177.3
    }
  ]
}